geomob/__init__.py
geomob/plot.py
geomob/preprocess.py
geomob/retrieve.py
geomob/routing.py
geomob/tessellate.py
geomob-0.1.1.dist-info/METADATA
geomob-0.1.1.dist-info/WHEEL
geomob-0.1.1.dist-info/licenses/LICENSE
geomob-0.1.1.dist-info/RECORD
