Metadata-Version: 2.4
Name: geomob
Version: 0.1.1
Summary: Geospatial and mobility data library
Project-URL: Homepage, https://github.com/lwdovico/geomob
Author-email: Ludovico Lemma <lwdovico@protonmail.com>
License-Expression: MIT
License-File: LICENSE
Classifier: Programming Language :: Python :: 3
Requires-Python: >=3.8
Requires-Dist: geopandas>=0.13.2
Requires-Dist: h3==3.7.7
Requires-Dist: haversine==2.8.1
Requires-Dist: keplergl==0.3.2
Requires-Dist: numpy>=1.23.5
Requires-Dist: pandas>=2.0.3
Requires-Dist: pygeohash==1.2.0
Requires-Dist: pytess==1.0.0
Requires-Dist: requests>=2.31.0
Requires-Dist: s2cell==1.8.0
Requires-Dist: shapely>=2.0.0
